imas_data_dictionaries/__init__.py
imas_data_dictionaries/imas_data_dictionaries.zip
imas_data_dictionaries-4.1.1.dist-info/licenses/LICENSE-CC-BY-ND
imas_data_dictionaries-4.1.1.dist-info/licenses/LICENSE-LGPL
imas_data_dictionaries-4.1.1.dist-info/METADATA
imas_data_dictionaries-4.1.1.dist-info/WHEEL
imas_data_dictionaries-4.1.1.dist-info/top_level.txt
imas_data_dictionaries-4.1.1.dist-info/RECORD
