Metadata-Version: 2.4
Name: imas-data-dictionaries
Version: 4.1.1
Summary: This package all released versions (IDSDef.xml + identifiers) of the Data Dictionary of ITER's Integrated Modelling & Analysis Suite (IMAS)
Author-email: ITER Organization <imas-support@iter.org>
License-Expression: LGPL-3.0+ AND CC-BY-ND-4.0
Project-URL: homepage, https://github.com/iterorganization/IMAS-Data-Dictionaries
Keywords: IMAS,Data Dictionary,IDS
Classifier: Intended Audience :: Developers
Classifier: Intended Audience :: Science/Research
Classifier: Programming Language :: Python :: 3
Classifier: Topic :: Scientific/Engineering :: Physics
License-File: LICENSE-LGPL
License-File: LICENSE-CC-BY-ND
Requires-Dist: importlib_resources; python_version < "3.9"
Requires-Dist: packaging
Dynamic: license-file
